celldetection/__init__.py
celldetection/__meta__.py
celldetection/callbacks/__init__.py
celldetection/callbacks/dropout.py
celldetection/callbacks/keepalive.py
celldetection/data/__init__.py
celldetection/data/cpn.py
celldetection/data/instance_eval.py
celldetection/data/misc.py
celldetection/data/segmentation.py
celldetection/data/toydata.py
celldetection/data/transforms.py
celldetection/data/datasets/__init__.py
celldetection/data/datasets/bbbc038.py
celldetection/data/datasets/bbbc039.py
celldetection/data/datasets/bbbc041.py
celldetection/data/datasets/generic.py
celldetection/data/datasets/synth.py
celldetection/models/__init__.py
celldetection/models/commons.py
celldetection/models/convnext.py
celldetection/models/convnextv2.py
celldetection/models/cpn.py
celldetection/models/densenet.py
celldetection/models/features.py
celldetection/models/filters.py
celldetection/models/fpn.py
celldetection/models/inference.py
celldetection/models/lightning_base.py
celldetection/models/lightning_cpn.py
celldetection/models/loss.py
celldetection/models/mamba.py
celldetection/models/manet.py
celldetection/models/mobilenetv3.py
celldetection/models/normalization.py
celldetection/models/ppm.py
celldetection/models/resnet.py
celldetection/models/smp.py
celldetection/models/timmodels.py
celldetection/models/unet.py
celldetection/mpi/__init__.py
celldetection/mpi/mpi.py
celldetection/ops/__init__.py
celldetection/ops/boxes.py
celldetection/ops/commons.py
celldetection/ops/cpn.py
celldetection/ops/draw.py
celldetection/ops/features.py
celldetection/ops/loss.py
celldetection/ops/normalization.py
celldetection/optim/__init__.py
celldetection/optim/lr_scheduler.py
celldetection/util/__init__.py
celldetection/util/logging.py
celldetection/util/schedule.py
celldetection/util/shm_cache.py
celldetection/util/timer.py
celldetection/util/util.py
celldetection/visualization/__init__.py
celldetection/visualization/cmaps.py
celldetection/visualization/images.py
CellDetection-0.4.9.dist-info/LICENSE
CellDetection-0.4.9.dist-info/METADATA
CellDetection-0.4.9.dist-info/WHEEL
CellDetection-0.4.9.dist-info/entry_points.txt
CellDetection-0.4.9.dist-info/top_level.txt
CellDetection-0.4.9.dist-info/RECORD
