Metadata-Version: 2.1
Name: CellDetection
Version: 0.4.9
Summary: Cell Detection with PyTorch.
Home-page: https://celldetection.org
Author: Eric Upschulte
Author-email: e.upschulte@fz-juelich.de
License: Apache License, Version 2.0
Keywords: cell,detection,object,segmentation,pytorch,cpn,contour,proposal,network,deep,learning,unet,fzj,julich,juelich,ai
Classifier: Topic :: Scientific/Engineering :: Artificial Intelligence
Classifier: Topic :: Scientific/Engineering :: Medical Science Apps.
Classifier: License :: OSI Approved :: Apache Software License
Classifier: Operating System :: OS Independent
License-File: LICENSE
Requires-Dist: numpy
Requires-Dist: matplotlib
Requires-Dist: scipy
Requires-Dist: scikit-image
Requires-Dist: opencv-python
Requires-Dist: torch >=2.0.0
Requires-Dist: torchvision
Requires-Dist: tensorboard
Requires-Dist: seaborn
Requires-Dist: tqdm
Requires-Dist: h5py
Requires-Dist: pillow
Requires-Dist: nvidia-ml-py
Requires-Dist: albumentations >=1.3.0
Requires-Dist: timm
Requires-Dist: segmentation-models-pytorch
Requires-Dist: pandas
Requires-Dist: pytorch-lightning
Requires-Dist: pyyaml
